scrapegraph_mcp/__init__.py
scrapegraph_mcp/py.typed
scrapegraph_mcp/server.py
mseep_scrapegraph_mcp-1.0.4.dist-info/METADATA
mseep_scrapegraph_mcp-1.0.4.dist-info/WHEEL
mseep_scrapegraph_mcp-1.0.4.dist-info/entry_points.txt
mseep_scrapegraph_mcp-1.0.4.dist-info/licenses/LICENSE
mseep_scrapegraph_mcp-1.0.4.dist-info/RECORD
