Metadata-Version: 2.4
Name: mseep-scrapegraph-mcp
Version: 1.0.4
Summary: MCP server for ScapeGraph API integration
Project-URL: Homepage, https://github.com/ScrapeGraphAI/scrapegraph-mcp
Project-URL: Bug Tracker, https://github.com/ScrapeGraphAI/scrapegraph-mcp/issues
Author-email: mseep <support@skydeck.ai>
License: MIT
License-File: LICENSE
Classifier: Development Status :: 4 - Beta
Classifier: Intended Audience :: Developers
Classifier: License :: OSI Approved :: MIT License
Classifier: Programming Language :: Python :: 3
Classifier: Programming Language :: Python :: 3.10
Classifier: Topic :: Software Development :: Libraries :: Python Modules
Requires-Python: >=3.10
Requires-Dist: httpx>=0.24.0
Requires-Dist: mcp[cli]>=1.3.0
Provides-Extra: dev
Requires-Dist: mypy>=1.0.0; extra == 'dev'
Requires-Dist: ruff>=0.1.0; extra == 'dev'
